m3tl/__init__.py
m3tl/_nbdev.py
m3tl/base_params.py
m3tl/input_fn.py
m3tl/model_fn.py
m3tl/modeling.py
m3tl/params.py
m3tl/preproc_decorator.py
m3tl/pyspark_utils.py
m3tl/read_write_tfrecord.py
m3tl/run_bert_multitask.py
m3tl/special_tokens.py
m3tl/test_base.py
m3tl/tutorial.py
m3tl/utils.py
m3tl/bert_preprocessing/__init__.py
m3tl/bert_preprocessing/bert_utils.py
m3tl/bert_preprocessing/create_bert_features.py
m3tl/embedding_layer/__init__.py
m3tl/embedding_layer/base.py
m3tl/loss_strategy/__init__.py
m3tl/loss_strategy/base.py
m3tl/mtl_model/__init__.py
m3tl/mtl_model/base.py
m3tl/mtl_model/mmoe.py
m3tl/predefined_problems/__init__.py
m3tl/predefined_problems/cws_data.py
m3tl/predefined_problems/ner_data.py
m3tl/predefined_problems/test_data.py
m3tl/problem_types/__init__.py
m3tl/problem_types/cls.py
m3tl/problem_types/contrastive_learning.py
m3tl/problem_types/masklm.py
m3tl/problem_types/multi_cls.py
m3tl/problem_types/premask_mlm.py
m3tl/problem_types/pretrain.py
m3tl/problem_types/regression.py
m3tl/problem_types/seq2seq_text.py
m3tl/problem_types/seq_tag.py
m3tl/problem_types/utils.py
m3tl/problem_types/vector_fit.py
m3tl-0.7.0.dist-info/LICENSE
m3tl-0.7.0.dist-info/METADATA
m3tl-0.7.0.dist-info/WHEEL
m3tl-0.7.0.dist-info/top_level.txt
m3tl-0.7.0.dist-info/RECORD
